keysight/__init__.py
keysight/e4411b.py
keysight/n9038.py
keysight/n9340.py
keysight-1.5.0.dist-info/METADATA
keysight-1.5.0.dist-info/WHEEL
keysight-1.5.0.dist-info/licenses/AUTHORS.md
keysight-1.5.0.dist-info/licenses/LICENSE.txt
keysight-1.5.0.dist-info/RECORD
