Metadata-Version: 2.3
Name: keysight
Version: 1.5.0
Summary: Package for working with Keysight/Agilent test equipment
Project-URL: Homepage, https://github.com/questrail/keysight
Project-URL: Issues, https://github.com/questrail/keysight/issues
Author-email: Matthew Rankin <matthew@questrail.com>
Classifier: Development Status :: 5 - Production/Stable
Classifier: Intended Audience :: Developers
Classifier: License :: OSI Approved :: MIT License
Classifier: Operating System :: OS Independent
Classifier: Programming Language :: Python
Classifier: Programming Language :: Python :: 3
Classifier: Programming Language :: Python :: 3.9
Classifier: Programming Language :: Python :: 3.10
Classifier: Programming Language :: Python :: 3.11
Classifier: Programming Language :: Python :: 3.12
Classifier: Programming Language :: Python :: 3.13
Classifier: Topic :: Software Development :: Libraries :: Python Modules
Requires-Python: >=3.9
Requires-Dist: numpy>=1.26.0
